{
	"DEFAULT":{
		"1":" issuer:"
		,"2":" subject:"
		,"3":"Missing required option 'cert'."
		,"4":"Missing required option 'country'."
		,"5":"Missing required option 'key' or 'cert'."
		,"6":"Missing required option 'key'."
		,"7":"Missing required option 'locality'(city)."
		,"8":"Missing required option 'name'."
		,"9":"Missing required option 'org'."
		,"10":"Missing required option 'request'."
		,"11":"Missing required option 'serial'."
		,"12":"Missing required option 'signer'."
		,"13":"Missing required option 'state' or province."
		,"14":"Reviver parameter is not a function."
		,"15":"Something"
		,"16":"Volume failed to open."
		,"23":"expiration : failed to parse cert"
		,"17":"gencert : bad pubkey specified."
		,"18":"pubkey: bad key or password"
		,"19":"validate: bad certificate"
		,"20":"validate: certificate signature failed:"
		,"21":"validate: failed; unhandled error:"
		,"22":"validate: unable to get issuer cert locally."
	}
}
